meteoclimatic/__init__.py
meteoclimatic/client.py
meteoclimatic/exceptions.py
meteoclimatic/feed.py
meteoclimatic/observation.py
meteoclimatic/station.py
meteoclimatic/weather.py
pymeteoclimatic-0.1.1.dist-info/LICENSE
pymeteoclimatic-0.1.1.dist-info/METADATA
pymeteoclimatic-0.1.1.dist-info/WHEEL
pymeteoclimatic-0.1.1.dist-info/top_level.txt
pymeteoclimatic-0.1.1.dist-info/RECORD
