Metadata-Version: 2.1
Name: pymeteoclimatic
Version: 0.1.1
Summary: A Python wrapper around the Meteoclimatic service
Author-email: Adrián Moreno <adrian@morenomartinez.com>
License: MIT
Project-URL: Homepage, https://github.com/adrianmo/pymeteoclimatic
Project-URL: Repository, https://github.com/adrianmo/pymeteoclimatic
Keywords: meteoclimatic,client,library,api,weather
Classifier: License :: OSI Approved :: MIT License
Classifier: Programming Language :: Python
Classifier: Programming Language :: Python :: 3
Classifier: Programming Language :: Python :: 3 :: Only
Classifier: Programming Language :: Python :: 3.8
Classifier: Programming Language :: Python :: 3.9
Classifier: Programming Language :: Python :: 3.10
Classifier: Programming Language :: Python :: 3.11
Classifier: Programming Language :: Python :: 3.12
Classifier: Natural Language :: English
Classifier: Operating System :: OS Independent
Classifier: Development Status :: 5 - Production/Stable
Classifier: Intended Audience :: Developers
Classifier: Topic :: Software Development :: Libraries
Requires-Python: >=3.8
License-File: LICENSE
Requires-Dist: lxml>=4.5
Requires-Dist: beautifulsoup4>=4.9
